ai_engine_sdk/__init__.py
ai_engine_sdk/api_models/__init__.py
ai_engine_sdk/api_models/agents_json_messages.py
ai_engine_sdk/api_models/api_message.py
ai_engine_sdk/api_models/api_models.py
ai_engine_sdk/api_models/parsing_utils.py
ai_engine_sdk/client.py
ai_engine_sdk/llm_models.py
ai_engine_sdk/use_cases/__init__.py
ai_engine_sdk/use_cases/create_function_group_and_share.py
ai_engine_sdk-0.1.2.dist-info/LICENSE
ai_engine_sdk-0.1.2.dist-info/METADATA
ai_engine_sdk-0.1.2.dist-info/WHEEL
ai_engine_sdk-0.1.2.dist-info/RECORD
