Metadata-Version: 2.1
Name: ai-engine-sdk
Version: 0.1.2
Summary: 
Author: Xavier
Author-email: xavier.peiro@fetch.ai
Requires-Python: >=3.10,<3.13
Classifier: Programming Language :: Python :: 3
Classifier: Programming Language :: Python :: 3.10
Classifier: Programming Language :: Python :: 3.11
Classifier: Programming Language :: Python :: 3.12
Requires-Dist: aiohttp (>=3.9.5,<4.0.0)
Requires-Dist: pydantic (>=1.10.7,<2.0.0)
Requires-Dist: python-dotenv (>=1.0.1,<1.1.0)
